LICENSE
README.md
setup.py
funpredict/__init__.py
funpredict/fun_model.py
funpredict/utils.py
funpredict.egg-info/PKG-INFO
funpredict.egg-info/SOURCES.txt
funpredict.egg-info/dependency_links.txt
funpredict.egg-info/requires.txt
funpredict.egg-info/top_level.txt
test/test.py