Metadata-Version: 2.1
Name: funpredict
Version: 0.0.3
Summary: Introducing Fun Predict, the ultimate time-saver for machine learning! No more complex coding or tedious parameter tuning - just sit back and let Fun Predict build your basic models with ease. It's like having a personal assistant for your machine learning projects, making the process simple, efficient, and, well, Fun! 🛋
Author: Sushanta Das
Author-email: <imachi@skiff.com>
Keywords: python,scikit-learn,machine learning,deep learning,Computer Vision,Artificial intelligence
License-File: LICENSE
